refcheck/__init__.py
refcheck/cli.py
refcheck/log_conf.py
refcheck/main.py
refcheck/parsers.py
refcheck/settings.py
refcheck/utils.py
refcheck/validators.py
refcheck-0.4.2.dist-info/METADATA
refcheck-0.4.2.dist-info/WHEEL
refcheck-0.4.2.dist-info/entry_points.txt
refcheck-0.4.2.dist-info/licenses/LICENSE
refcheck-0.4.2.dist-info/RECORD
