Metadata-Version: 2.4
Name: refcheck
Version: 0.4.2
Summary: Tool for finding broken references and links in Markdown files.
License-File: LICENSE
Keywords: markdown,links,references,validator,cli
Author: Sebastian Flum
Author-email: sebastian.flum.dev@gmail.com
Requires-Python: >=3.10,<4.0
Classifier: Programming Language :: Python :: 3
Classifier: Programming Language :: Python :: 3.10
Classifier: Programming Language :: Python :: 3.11
Classifier: Programming Language :: Python :: 3.12
Classifier: Programming Language :: Python :: 3.13
Classifier: Programming Language :: Python :: 3.14
Requires-Dist: requests (>=2.32.3,<3.0.0)
Project-URL: Repository, https://github.com/flumi3/markdown-refcheck
